bibt/gcp/pubsub/__init__.py
bibt/gcp/pubsub/classes.py
bibt/gcp/pubsub/methods.py
bibt/gcp/pubsub/params.py
bibt/gcp/pubsub/version.py
bibt_gcp_pubsub-0.0.22.dist-info/METADATA
bibt_gcp_pubsub-0.0.22.dist-info/WHEEL
bibt_gcp_pubsub-0.0.22.dist-info/licenses/LICENSE
bibt_gcp_pubsub-0.0.22.dist-info/RECORD
