Metadata-Version: 2.4
Name: bibt-gcp-pubsub
Version: 0.0.22
Summary: Functionality often used by BITS Blue Team (PubSub module).
Project-URL: Bug Tracker, https://github.com/broadinstitute/bibt-gcp-pubsub/issues
Project-URL: Documentation, https://bibt-gcp-pubsub.readthedocs.io/en/latest/
Project-URL: Homepage, https://github.com/broadinstitute/bibt-gcp-pubsub
Author-email: Matthew OBrien <mobrien@broadinstitute.org>
License-File: LICENSE
Classifier: License :: OSI Approved :: MIT License
Classifier: Operating System :: OS Independent
Classifier: Programming Language :: Python :: 3
Classifier: Programming Language :: Python :: 3.9
Classifier: Programming Language :: Python :: 3.10
Classifier: Programming Language :: Python :: 3.11
Classifier: Programming Language :: Python :: 3.12
Classifier: Topic :: Security
Classifier: Topic :: Software Development :: Libraries
Classifier: Topic :: Utilities
Requires-Python: >=3.7
Requires-Dist: cloudevents==1.10.1
Requires-Dist: google-cloud-functions==1.16.0
Requires-Dist: google-cloud-pubsub==2.19.0
Requires-Dist: python-dateutil==2.8.2
